Artifice/Artifice.py
Artifice/__init__.py
Artifice/activation_funcs_library.txt
Artifice/loss_funcs_library.txt
Artifice-0.0.5.dist-info/LICENSE
Artifice-0.0.5.dist-info/METADATA
Artifice-0.0.5.dist-info/WHEEL
Artifice-0.0.5.dist-info/top_level.txt
Artifice-0.0.5.dist-info/RECORD
