Metadata-Version: 2.1
Name: Artifice
Version: 0.0.5
Summary: A homemade machine learning platform modeled after TensorFlow
Author-email: William Bidle <wkb15@scarletmail.rutgers.edu>, Ilana Zane <ilanazane@comcast.net>
Maintainer-email: William Bidle <wkb15@scarletmail.rutgers.edu>, Ilana Zane <ilanazane@comcast.net>
Project-URL: Homepage, https://github.com/WilliamBidle/Artifice
Project-URL: Bug Tracker, https://github.com/WilliamBidle/Artifice/issues
Classifier: Programming Language :: Python :: 3
Classifier: License :: OSI Approved :: MIT License
Classifier: Operating System :: OS Independent
Requires-Python: >=3.7
License-File: LICENSE
